deluged_client/__init__.py
deluged_client/client.py
deluged_client/errors.py
deluged_client/protocol.py
deluged_client/rencode.py
deluged_client/util.py
deluged_client-0.0.1.dist-info/METADATA
deluged_client-0.0.1.dist-info/RECORD
deluged_client-0.0.1.dist-info/WHEEL
deluged_client-0.0.1.dist-info/top_level.txt
